odoo/addons/sale_substate/README.rst
odoo/addons/sale_substate/__init__.py
odoo/addons/sale_substate/__manifest__.py
odoo/addons/sale_substate/data/sale_substate_data.xml
odoo/addons/sale_substate/data/sale_substate_demo.xml
odoo/addons/sale_substate/data/sale_substate_mail_template_data.xml
odoo/addons/sale_substate/i18n/es.po
odoo/addons/sale_substate/i18n/it.po
odoo/addons/sale_substate/i18n/sale_substate.pot
odoo/addons/sale_substate/models/__init__.py
odoo/addons/sale_substate/models/sale_order.py
odoo/addons/sale_substate/readme/CONTRIBUTORS.md
odoo/addons/sale_substate/readme/DESCRIPTION.md
odoo/addons/sale_substate/readme/USAGE.md
odoo/addons/sale_substate/static/description/icon.png
odoo/addons/sale_substate/static/description/index.html
odoo/addons/sale_substate/tests/__init__.py
odoo/addons/sale_substate/tests/test_sale_substate.py
odoo/addons/sale_substate/views/sale_views.xml
odoo_addon_sale_substate-18.0.1.0.0.2.dist-info/METADATA
odoo_addon_sale_substate-18.0.1.0.0.2.dist-info/WHEEL
odoo_addon_sale_substate-18.0.1.0.0.2.dist-info/top_level.txt
odoo_addon_sale_substate-18.0.1.0.0.2.dist-info/RECORD
